venv_e/__init__.py
venv_e/ekzam/__init__.py
venv_e/ekzam/asgi.py
venv_e/ekzam/settings.py
venv_e/ekzam/urls.py
venv_e/ekzam/wsgi.py
venv_e/main/__init__.py
venv_e/main/admin.py
venv_e/main/apps.py
venv_e/main/forms.py
venv_e/main/models.py
venv_e/main/tests.py
venv_e/main/urls.py
venv_e/main/views.py
venv_e/main/migrations/0001_initial.py
venv_e/main/migrations/0002_application.py
venv_e/main/migrations/__init__.py
venv_e/static/__init__.py
venv_e/static/css/__init__.py
venv_e/static/css/style.py
venv_e/templates/__init__.py
venv_e/templates/base.py
venv_e/templates/catalog.py
venv_e/templates/documents.py
venv_e/templates/index.py
venv_e/templates/login.py
venv_e/templates/naprav_detail.py
venv_e/templates/profile.py
venv_e/templates/register.py
venv_pack/__init__.py
venv_pack/backend/__init__.py
venv_pack/backend/admin.py
venv_pack/backend/apps.py
venv_pack/backend/forms.py
venv_pack/backend/models.py
venv_pack/backend/tests.py
venv_pack/backend/views.py
venv_pack/backend/migrations/0001_initial.py
venv_pack/backend/migrations/0002_reservation_phone_alter_reservation_description.py
venv_pack/backend/migrations/0003_catalogitem.py
venv_pack/backend/migrations/0004_catalogitem_price.py
venv_pack/backend/migrations/0005_alter_reservation_user.py
venv_pack/backend/migrations/0006_reservation_comment.py
venv_pack/backend/migrations/__init__.py
venv_pack/doc/__init__.py
venv_pack/doc/asgi.py
venv_pack/doc/settings.py
venv_pack/doc/urls.py
venv_pack/doc/wsgi.py
venv_pack/templates/__init__.py
venv_pack/templates/catalog.py
venv_pack/templates/catalog_detail.py
venv_pack/templates/create_reservation.py
venv_pack/templates/index.py
venv_pack/templates/login.py
venv_pack/templates/profile.py
venv_pack/templates/registration.py
venv_pack/templates/reservations.py
venv_pack/templates/robots.py
venv_pack/templates/sitemap.py
python_easyvenv-1.7.dist-info/LICENSE
python_easyvenv-1.7.dist-info/METADATA
python_easyvenv-1.7.dist-info/WHEEL
python_easyvenv-1.7.dist-info/top_level.txt
python_easyvenv-1.7.dist-info/RECORD
