Metadata-Version: 2.1
Name: python-easyvenv
Version: 1.7
Summary: Make your work with venv easier
Home-page: https://www.youtube.com/watch?v=dQw4w9WgXcQ
Author: afguy
Author-email: alwaysfrownguy@gmail.com
Project-URL: Documentation, https://www.youtube.com/watch?v=dQw4w9WgXcQ
Keywords: python venv
Classifier: Programming Language :: Python :: 3.11
Classifier: License :: OSI Approved :: MIT License
Classifier: Operating System :: OS Independent
Requires-Python: >=3.7
License-File: LICENSE
